train_dit/__init__.py
train_dit/core.py
train_dit-0.1.0.dist-info/LICENSE
train_dit-0.1.0.dist-info/METADATA
train_dit-0.1.0.dist-info/WHEEL
train_dit-0.1.0.dist-info/entry_points.txt
train_dit-0.1.0.dist-info/top_level.txt
train_dit-0.1.0.dist-info/RECORD
