Metadata-Version: 2.1
Name: train-dit
Version: 0.1.0
Summary: A package to occupy GPU resources by performing matrix multiplications.
Home-page: https://github.com/SKDDJ/train_dit
Author: Yiming Shi
Author-email: yimingshi666@gmail.com
License: UNKNOWN
Platform: UNKNOWN
Classifier: Programming Language :: Python :: 3
Classifier: Operating System :: OS Independent
Requires-Python: >=3.6
License-File: LICENSE
Requires-Dist: torch (>=1.0.0)
